{
  "version": "1.0",
  "type": "repository",
  "interval": "day",
  "generatedAt": "2025-12-22T23:35:26.576Z",
  "items": [
    {
      "date": "2025-12-22",
      "sourceLastUpdated": "2025-12-22T23:35:26.575Z",
      "contentHash": "8e3862543b2271d801e1c3fd909f7311f1fa478b946061a077b4b9f6eb9b8862",
      "path": "2025-12-22.json"
    },
    {
      "date": "2025-12-21",
      "sourceLastUpdated": "2025-12-22T23:35:23.865Z",
      "contentHash": "de1f7b178cbe9478eae799901880d56f66af285dac1f9a1191c8c49c09d1107a",
      "path": "2025-12-21.json"
    },
    {
      "date": "2025-12-20",
      "sourceLastUpdated": "2025-12-21T23:35:42.336Z",
      "contentHash": "169e23ebaf4f81cedc5148910de60b86504fbf313492e1a7efd689f93e249fd0",
      "path": "2025-12-20.json"
    },
    {
      "date": "2025-12-19",
      "sourceLastUpdated": "2025-12-20T23:34:09.750Z",
      "contentHash": "7f00af7346024471af16d98ceff0f794dbe9c28d2fe59ad4af28d29006db96ea",
      "path": "2025-12-19.json"
    }
  ]
}