{
  "version": "1.0",
  "type": "contributor",
  "interval": "day",
  "date": "2025-12-19",
  "generatedAt": "2025-12-21T23:35:36.512Z",
  "sourceLastUpdated": "2025-12-21T23:35:36.512Z",
  "contentFormat": "markdown",
  "contentHash": "e4ced8ff2848e7c35ad8e8b41bd9d46adce06a7b721e9bd1835817ed6baa75ef",
  "entity": {
    "username": "smartcontracts"
  },
  "content": "smartcontracts: Focused on feature development and bug fixes, opening two new PRs in `ethereum-optimism/optimism` (#18661, #18659) and contributing 15 commits across 35 files with a net addition of over 900 lines of code, primarily in bugfix and feature work."
}