{
  "version": "1.0",
  "type": "contributor",
  "interval": "day",
  "date": "2025-12-24",
  "generatedAt": "2025-12-28T23:36:06.843Z",
  "sourceLastUpdated": "2025-12-28T23:36:06.843Z",
  "contentFormat": "markdown",
  "contentHash": "a4a947a99d5385e5ee4126c5e603b7b9db8302959946ff7160026623fe8dad42",
  "entity": {
    "username": "zjg555543"
  },
  "content": "zjg555543: Focused on feature development, opening a significant PR in ethereum-optimism/optimism (#18693) to add a configurable HTTP body limit, while also contributing to both bugfix and other work across 9 files with 2 commits."
}