{
  "interval": {
    "intervalStart": "2025-11-22T00:00:00.000Z",
    "intervalEnd": "2025-11-23T00:00:00.000Z",
    "intervalType": "day"
  },
  "repository": "ethereum-optimism/optimism",
  "overview": "From 2025-11-22 to 2025-11-23, ethereum-optimism/optimism had 2 new PRs (0 merged), 0 new issues, and 3 active contributors.",
  "topIssues": [],
  "topPRs": [
    {
      "id": "PR_kwDODjvEJM60_r4D",
      "title": "Update noop.go",
      "author": "Mmansoor89",
      "number": 18356,
      "body": "<!--\r\nContributions welcome! See https://github.com/ethereum-optimism/.github/blob/master/CONTRIBUTING.md\r\n-->\r\n\r\n**Description**\r\n\r\n<!--\r\nA clear and concise description of the features you're adding in this pull request.\r\n-->\r\n\r\n**Tests**\r\n\r\n<!--\r\nPlease describe any tests you've added. If you've added no tests, or left important behavior untested, please explain why not.\r\n-->\r\n\r\n**Additional context**\r\n\r\n<!--\r\nAdd any other context about the problem you're solving.\r\n-->\r\n\r\n**Metadata**\r\n\r\n<!-- \r\nInclude a link to any github issues that this may close in the following form:\r\n- Fixes #[Link to Issue]\r\n-->\r\n",
      "repository": "ethereum-optimism/optimism",
      "createdAt": "2025-11-22T17:36:23Z",
      "mergedAt": null,
      "additions": 47,
      "deletions": 12
    },
    {
      "id": "PR_kwDODjvEJM60_oWa",
      "title": "Update main.go",
      "author": "DoctorLambda",
      "number": 18355,
      "body": "<!--\r\nContributions welcome! See https://github.com/ethereum-optimism/.github/blob/master/CONTRIBUTING.md\r\n-->\r\n\r\n**Description**\r\n\r\n<!--\r\nA clear and concise description of the features you're adding in this pull request.\r\n-->\r\n\r\n**Tests**\r\n\r\n<!--\r\nPlease describe any tests you've added. If you've added no tests, or left important behavior untested, please explain why not.\r\n-->\r\n\r\n**Additional context**\r\n\r\n<!--\r\nAdd any other context about the problem you're solving.\r\n-->\r\n\r\n**Metadata**\r\n\r\n<!-- \r\nInclude a link to any github issues that this may close in the following form:\r\n- Fixes #[Link to Issue]\r\n-->\r\n",
      "repository": "ethereum-optimism/optimism",
      "createdAt": "2025-11-22T17:15:23Z",
      "mergedAt": null,
      "additions": 28,
      "deletions": 13
    },
    {
      "id": "PR_kwDODjvEJM6ugJDT",
      "title": "fix(op-chain-ops): use correct file permissions for debug_witness.json",
      "author": "anim001k",
      "number": 17926,
      "body": "\r\n\r\n## Description\r\nThe `debug_witness.json` file was being created with executable permissions (`0755`) instead of standard read-write permissions for data files.\r\n\r\n### Solution\r\nChanged file permissions from `0755` to `0644` when writing the debug witness JSON file.\r\n\r\n",
      "repository": "ethereum-optimism/optimism",
      "createdAt": "2025-10-19T09:53:52Z",
      "mergedAt": null,
      "additions": 1,
      "deletions": 1
    }
  ],
  "codeChanges": {
    "additions": 0,
    "deletions": 0,
    "files": 0,
    "commitCount": 2
  },
  "completedItems": [],
  "topContributors": [
    {
      "username": "Mmansoor89",
      "avatarUrl": "https://avatars.githubusercontent.com/u/97762760?u=8a6ba86409b27eaff7b8b410982da9b08f2f28e4&v=4",
      "totalScore": 7.8921722811110495,
      "prScore": 7.8921722811110495,
      "issueScore": 0,
      "reviewScore": 0,
      "commentScore": 0,
      "summary": "Mmansoor89: Focused on code maintenance, opening one pull request, ethereum-optimism/optimism#18356, to update `noop.go` with 47 additions and 12 deletions."
    },
    {
      "username": "DoctorLambda",
      "avatarUrl": "https://avatars.githubusercontent.com/u/8275370?u=eb9cc86d8eaebb935cf306949c8765b19dd0737c&v=4",
      "totalScore": 7.713834809141684,
      "prScore": 7.713834809141684,
      "issueScore": 0,
      "reviewScore": 0,
      "commentScore": 0,
      "summary": "DoctorLambda: Today, DoctorLambda opened a pull request in ethereum-optimism/optimism (#18355) to update `main.go`, modifying 1 file with 28 additions and 13 deletions, indicating a focus on other work."
    }
  ],
  "newPRs": 2,
  "mergedPRs": 0,
  "newIssues": 0,
  "closedIssues": 0,
  "activeContributors": 3
}