{
  "version": "1.0",
  "type": "repository",
  "interval": "week",
  "date": "2025-12-28",
  "generatedAt": "2025-12-31T23:35:19.940Z",
  "sourceLastUpdated": "2025-12-31T23:35:19.940Z",
  "contentFormat": "markdown",
  "contentHash": "bfd28b96d8e119d4bd5b85eed1de08646682ec19d6c29d181f2a59867e1c2735",
  "entity": {
    "repoId": "ethereum-optimism/ethereum-optimism.github.io",
    "owner": "ethereum-optimism",
    "repo": "ethereum-optimism.github.io"
  },
  "content": "# ethereum-optimism/ethereum-optimism.github.io Weekly Report (Dec 28 - 3, 2025)\n\n## 🚀 Highlights\nThis week's development activity centered on expanding the ecosystem's token offerings. A new pull request was opened to add the PAGE token to the Base network, reflecting ongoing efforts to integrate more assets into the Superchain. Overall, it was a focused week with development concentrated on this specific addition, and no new or closed issues were reported.\n\n## 🛠️ Key Developments\nWork this week focused on growing the list of supported tokens within the ecosystem.\n\n- **New Token Listing**\n  - A pull request ([#1250](https://github.com/ethereum-optimism/ethereum-optimism.github.io/pull/1250)) was opened to add the PAGE token to Base. This contributes to the broader goal of expanding the variety of assets available across the Superchain.\n\n## 🐛 Issues & Triage\nAccording to the provided reports, there was no activity related to issues this week.\n\n- **Closed Issues:** No issues were closed during this period.\n- **New & Active Issues:** No new issues were opened, and no updates on active issues were reported.\n\n## 💬 Community & Collaboration\nThe provided daily reports did not contain specific details regarding community discussions, contributor collaborations, or review activity for this period."
}